mshoot/__init__.py
mshoot-0.0.2.dev0.dist-info/METADATA
mshoot-0.0.2.dev0.dist-info/RECORD
mshoot-0.0.2.dev0.dist-info/WHEEL
mshoot-0.0.2.dev0.dist-info/top_level.txt
